Metadata-Version: 2.1
Name: sweetspot-sdk
Version: 0.1.5
Summary: SDK for Sweetspot Team to interact with backend APIs
Home-page: https://www.sweetspot.so
Author: Philip Kung
Author-email: philip@sweetspot.so
License: UNKNOWN
Platform: UNKNOWN
Requires-Dist: requests (<3.0,>=2.9.1)
Requires-Dist: jsonpickle (>=1.4,>=1.4.1)
Requires-Dist: python-dateutil (<3.0,>=2.5.3)
Requires-Dist: deprecation (>=2.0.6)
